r3stapi
