Metadata-Version: 1.0
Name: r3stapi
Version: 0.6.2
Summary: Some description.
Home-page: http://github.com/vandenberghinc/r3stapi
Author: Daan van den Bergh
Author-email: vandenberghinc.contact@gmail.com
License: MIT
Platform: UNKNOWN
